autoapi/__init__.py
autoapi/backends.py
autoapi/directives.py
autoapi/documenters.py
autoapi/extension.py
autoapi/inheritance_diagrams.py
autoapi/settings.py
autoapi/toctree.py
autoapi/mappers/__init__.py
autoapi/mappers/base.py
autoapi/mappers/dotnet.py
autoapi/mappers/go.py
autoapi/mappers/javascript.py
autoapi/mappers/python/__init__.py
autoapi/mappers/python/astroid_utils.py
autoapi/mappers/python/mapper.py
autoapi/mappers/python/objects.py
autoapi/mappers/python/parser.py
autoapi/templates/index.rst
autoapi/templates/base/base.md
autoapi/templates/base/base.rst
autoapi/templates/dotnet/base_detail.rst
autoapi/templates/dotnet/base_embed.rst
autoapi/templates/dotnet/base_list.rst
autoapi/templates/dotnet/class.rst
autoapi/templates/dotnet/constructor.rst
autoapi/templates/dotnet/delegate.rst
autoapi/templates/dotnet/enum.rst
autoapi/templates/dotnet/event.rst
autoapi/templates/dotnet/field.rst
autoapi/templates/dotnet/interface.rst
autoapi/templates/dotnet/method.rst
autoapi/templates/dotnet/namespace.rst
autoapi/templates/dotnet/operator.rst
autoapi/templates/dotnet/property.rst
autoapi/templates/dotnet/struct.rst
autoapi/templates/go/base_member.rst
autoapi/templates/go/const.rst
autoapi/templates/go/func.rst
autoapi/templates/go/method.rst
autoapi/templates/go/package.rst
autoapi/templates/go/type.rst
autoapi/templates/go/var.rst
autoapi/templates/javascript/class.rst
autoapi/templates/javascript/function.rst
autoapi/templates/javascript/member.rst
autoapi/templates/javascript/module.rst
autoapi/templates/python/attribute.md
autoapi/templates/python/attribute.rst
autoapi/templates/python/class.md
autoapi/templates/python/class.rst
autoapi/templates/python/data.md
autoapi/templates/python/data.rst
autoapi/templates/python/exception.md
autoapi/templates/python/exception.rst
autoapi/templates/python/function.md
autoapi/templates/python/function.rst
autoapi/templates/python/method.md
autoapi/templates/python/method.rst
autoapi/templates/python/module.md
sphinx_autoapi2-2.0.1.1.dist-info/LICENSE.rst
sphinx_autoapi2-2.0.1.1.dist-info/WHEEL
sphinx_autoapi2-2.0.1.1.dist-info/METADATA
sphinx_autoapi2-2.0.1.1.dist-info/RECORD
