Metadata-Version: 2.1
Name: sphinx-autoapi2
Version: 2.0.1.1
Summary: Sphinx API documentation generator
Author-email: Eric Holscher <eric@ericholscher.com>
Maintainer-email: Ashley Whetter <ashley@awhetter.co.uk>
Requires-Python: >=3.7
Classifier: Development Status :: 4 - Beta
Classifier: Environment :: Plugins
Classifier: Framework :: Sphinx :: Extension
Classifier: Intended Audience :: Developers
Classifier: License :: OSI Approved :: MIT License
Classifier: Natural Language :: English
Classifier: Programming Language :: Python
Classifier: Programming Language :: Python :: 3
Classifier: Programming Language :: Python :: 3.7
Classifier: Programming Language :: Python :: 3.8
Classifier: Programming Language :: Python :: 3.9
Classifier: Programming Language :: Python :: 3.10
Classifier: Programming Language :: Python :: 3.11
Requires-Dist: astroid>=2.7
Requires-Dist: Jinja2
Requires-Dist: PyYAML
Requires-Dist: sphinx>=4.0
Requires-Dist: unidecode
Requires-Dist: sphinx ; extra == "docs"
Requires-Dist: sphinx_rtd_theme ; extra == "docs"
Requires-Dist: sphinxcontrib-dotnetdomain ; extra == "dotnet"
Requires-Dist: sphinxcontrib-golangdomain ; extra == "go"
Project-URL: Documentation, https://sphinx-autoapi.readthedocs.io/en/latest/
Project-URL: Homepage, http://github.com/readthedocs/sphinx-autoapi
Provides-Extra: docs
Provides-Extra: dotnet
Provides-Extra: go
